wagtail_filter_persistence/__init__.py
wagtail_filter_persistence/apps.py
wagtail_filter_persistence/middleware.py
wagtail_filter_persistence/wagtail_hooks.py
wagtail_filter_persistence-0.1.6.dist-info/licenses/LICENSE
wagtail_filter_persistence-0.1.6.dist-info/METADATA
wagtail_filter_persistence-0.1.6.dist-info/WHEEL
wagtail_filter_persistence-0.1.6.dist-info/top_level.txt
wagtail_filter_persistence-0.1.6.dist-info/RECORD
