Metadata-Version: 2.4
Name: wagtail-filter-persistence
Version: 0.1.6
Summary: A Wagtail plugin that persists filter selections in admin listings
Home-page: https://github.com/indigo7333/wagtail-filter-persistence
Author: Emil P
Author-email: emil@verdatek.com
Classifier: Programming Language :: Python :: 3
Classifier: License :: OSI Approved :: MIT License
Classifier: Operating System :: OS Independent
Classifier: Framework :: Django
Classifier: Framework :: Wagtail
Classifier: Framework :: Wagtail :: 5
Requires-Python: >=3.6
License-File: LICENSE
Requires-Dist: wagtail>=2.15
Dynamic: author
Dynamic: author-email
Dynamic: classifier
Dynamic: description
Dynamic: description-content-type
Dynamic: home-page
Dynamic: license-file
Dynamic: requires-dist
Dynamic: requires-python
Dynamic: summary
